README.md
setup.cfg
setup.py
shapSD/__init__.py
shapSD.egg-info/PKG-INFO
shapSD.egg-info/SOURCES.txt
shapSD.egg-info/dependency_links.txt
shapSD.egg-info/requires.txt
shapSD.egg-info/top_level.txt
shapSD/feature_explainer/__init__.py
shapSD/feature_explainer/binary_flip.py
shapSD/feature_explainer/data_encoding.py
shapSD/feature_explainer/decision_tree_explain.py
shapSD/feature_explainer/explanation_report.py
shapSD/feature_explainer/feature_importance.py
shapSD/feature_explainer/feature_processing.py
shapSD/feature_explainer/global_explainer.py
shapSD/feature_explainer/lime_explainer.py
shapSD/feature_explainer/local_explainer.py
shapSD/feature_explainer/logging_custom.py
shapSD/feature_explainer/model_init.py
shapSD/feature_explainer/numeric_perturb.py
shapSD/feature_explainer/pattern_explainer.py
shapSD/feature_explainer/shap_explainer.py
shapSD/feature_explainer/text_explainer.py
shapSD/feature_explainer/utils.py
shapSD/feature_explainer/word_explainer.py
shapSD/pysubgroup/__init__.py
shapSD/pysubgroup/algorithms.py
shapSD/pysubgroup/complex_target.py
shapSD/pysubgroup/fi_target.py
shapSD/pysubgroup/measures.py
shapSD/pysubgroup/nominal_target.py
shapSD/pysubgroup/numeric_target.py
shapSD/pysubgroup/subgroup.py
shapSD/pysubgroup/utils.py
shapSD/pysubgroup/visualization.py